cocotbext/axi/__init__.py
cocotbext/axi/address_space.py
cocotbext/axi/axi_channels.py
cocotbext/axi/axi_master.py
cocotbext/axi/axi_ram.py
cocotbext/axi/axi_slave.py
cocotbext/axi/axil_channels.py
cocotbext/axi/axil_master.py
cocotbext/axi/axil_ram.py
cocotbext/axi/axil_slave.py
cocotbext/axi/axis.py
cocotbext/axi/buddy_allocator.py
cocotbext/axi/constants.py
cocotbext/axi/memory.py
cocotbext/axi/reset.py
cocotbext/axi/sparse_memory.py
cocotbext/axi/stream.py
cocotbext/axi/utils.py
cocotbext/axi/version.py
cocotbext_axi-0.1.24.dist-info/LICENSE
cocotbext_axi-0.1.24.dist-info/METADATA
cocotbext_axi-0.1.24.dist-info/WHEEL
cocotbext_axi-0.1.24.dist-info/top_level.txt
cocotbext_axi-0.1.24.dist-info/RECORD
