Metadata-Version: 2.1
Name: cocotbext-axi
Version: 0.1.24
Summary: AXI, AXI lite, and AXI stream modules for cocotb
Home-page: https://github.com/alexforencich/cocotbext-axi
Download-URL: https://github.com/alexforencich/cocotbext-axi/tarball/master
Author: Alex Forencich
Author-email: alex@alexforencich.com
License: MIT
Project-URL: Bug Tracker, https://github.com/alexforencich/cocotbext-axi/issues
Project-URL: Source Code, https://github.com/alexforencich/cocotbext-axi
Keywords: axi,cocotb
Platform: any
Classifier: Development Status :: 3 - Alpha
Classifier: Framework :: cocotb
Classifier: License :: OSI Approved :: MIT License
Classifier: Operating System :: OS Independent
Classifier: Programming Language :: Python :: 3
Classifier: Topic :: Scientific/Engineering :: Electronic Design Automation (EDA)
Requires-Python: >=3.6
Provides-Extra: test
License-File: LICENSE
